{"created_at": "Tue May 15 15:52:46 +0000 2018", "id": 996418119051726849, "id_str": "996418119051726849", "text": "@tweetmommybop @JSavoly Ms. Maxine \u201cImpeach Trump\u201d  Waters!!!! https://t.co/pnpQ2EgnLb", "truncated": false, "entities": {"hashtags": [], "symbols": [], "user_mentions": [{"screen_name": "tweetmommybop", "name": "MommaT", "id": 875311595286654976, "id_str": "875311595286654976", "indices": [0, 14]}, {"screen_name": "JSavoly", "name": "Jasper #\u03a9", "id": 519728191, "id_str": "519728191", "indices": [15, 23]}], "urls": [], "media": [{"id": 996418095450226691, "id_str": "996418095450226691", "indices": [63, 86], "media_url": "http://pbs.twimg.com/tweet_video_thumb/DdP8-oMVAAMck94.jpg", "media_url_https": "https://pbs.twimg.com/tweet_video_thumb/DdP8-oMVAAMck94.jpg", "url": "https://t.co/pnpQ2EgnLb", "display_url": "pic.twitter.com/pnpQ2EgnLb", "expanded_url": "https://twitter.com/NYNURSE10550/status/996418119051726849/photo/1", "type": "photo", "sizes": {"thumb": {"w": 150, "h": 150, "resize": "crop"}, "medium": {"w": 498, "h": 280, "resize": "fit"}, "small": {"w": 498, "h": 280, "resize": "fit"}, "large": {"w": 498, "h": 280, "resize": "fit"}}}]}, "extended_entities": {"media": [{"id": 996418095450226691, "id_str": "996418095450226691", "indices": [63, 86], "media_url": "http://pbs.twimg.com/tweet_video_thumb/DdP8-oMVAAMck94.jpg", "media_url_https": "https://pbs.twimg.com/tweet_video_thumb/DdP8-oMVAAMck94.jpg", "url": "https://t.co/pnpQ2EgnLb", "display_url": "pic.twitter.com/pnpQ2EgnLb", "expanded_url": "https://twitter.com/NYNURSE10550/status/996418119051726849/photo/1", "type": "animated_gif", "sizes": {"thumb": {"w": 150, "h": 150, "resize": "crop"}, "medium": {"w": 498, "h": 280, "resize": "fit"}, "small": {"w": 498, "h": 280, "resize": "fit"}, "large": {"w": 498, "h": 280, "resize": "fit"}}, "video_info": {"aspect_ratio": [249, 140], "variants": [{"bitrate": 0, "content_type": "video/mp4", "url": "https://video.twimg.com/tweet_video/DdP8-oMVAAMck94.mp4"}]}}]}, "metadata": {"iso_language_code": "en", "result_type": "recent"}, "source": "<a href=\"http://twitter.com/download/iphone\" rel=\"nofollow\">Twitter for iPhone</a>", "in_reply_to_status_id": 996031500679172096, "in_reply_to_status_id_str": "996031500679172096", "in_reply_to_user_id": 875311595286654976, "in_reply_to_user_id_str": "875311595286654976", "in_reply_to_screen_name": "tweetmommybop", "user": {"id": 32590073, "id_str": "32590073", "name": "I \u2764\ufe0f a Good Smokey eye  \ud83e\udd40\ud83c\udf69", "screen_name": "NYNURSE10550", "location": "With Barack Michelle Joe & HRC", "description": "\ud83d\udc78\ud83c\udffb \ud83c\uddf5\ud83c\uddf7 R.N. https://t.co/MCVQBNx1gl #supportPuertoRico", "url": null, "entities": {"description": {"urls": [{"url": "https://t.co/MCVQBNx1gl", "expanded_url": "http://hispanicfederation.org", "display_url": "hispanicfederation.org", "indices": [11, 34]}]}}, "protected": false, "followers_count": 2643, "friends_count": 2829, "listed_count": 17, "created_at": "Fri Apr 17 21:16:21 +0000 2009", "favourites_count": 301675, "utc_offset": -18000, "time_zone": "Central Time (US & Canada)", "geo_enabled": true, "verified": false, "statuses_count": 47336, "lang": "en", "contributors_enabled": false, "is_translator": false, "is_translation_enabled": false, "profile_background_color": "FF6699", "profile_background_image_url": "http://pbs.twimg.com/profile_background_images/168955621/mac.jpg", "profile_background_image_url_https": "https://pbs.twimg.com/profile_background_images/168955621/mac.jpg", "profile_background_tile": true, "profile_image_url": "http://pbs.twimg.com/profile_images/868627434165415936/n-vyCJGj_normal.jpg", "profile_image_url_https": "https://pbs.twimg.com/profile_images/868627434165415936/n-vyCJGj_normal.jpg", "profile_banner_url": "https://pbs.twimg.com/profile_banners/32590073/1486676338", "profile_link_color": "B40B43", "profile_sidebar_border_color": "CC3366", "profile_sidebar_fill_color": "E5507E", "profile_text_color": "362720", "profile_use_background_image": true, "has_extended_profile": false, "default_profile": false, "default_profile_image": false, "following": false, "follow_request_sent": false, "notifications": false, "translator_type": "none"}, "geo": null, "coordinates": null, "place": null, "contributors": null, "is_quote_status": false, "retweet_count": 2, "favorite_count": 4, "favorited": false, "retweeted": false, "possibly_sensitive": false, "lang": "en"}
